<annotation>
	<folder>new</folder>
	<filename>new_00000207.jpg</filename>
	<path>C:\Users\amit.gupta9\Projects\Fashion_Recommendation\google_downloads\new\new_00000207.jpg</path>
	<source>
		<database>Unknown</database>
	</source>
	<size>
		<width>325</width>
		<height>488</height>
		<depth>3</depth>
	</size>
	<segmented>0</segmented>
	<object>
		<name>sunglasses</name>
		<pose>Unspecified</pose>
		<truncated>0</truncated>
		<difficult>0</difficult>
		<bndbox>
			<xmin>108</xmin>
			<ymin>105</ymin>
			<xmax>137</xmax>
			<ymax>120</ymax>
		</bndbox>
	</object>
	<object>
		<name>jeans</name>
		<pose>Unspecified</pose>
		<truncated>0</truncated>
		<difficult>0</difficult>
		<bndbox>
			<xmin>107</xmin>
			<ymin>267</ymin>
			<xmax>197</xmax>
			<ymax>442</ymax>
		</bndbox>
	</object>
</annotation>
